[
  {
    "id": "local-1",
    "title": "    ",
    "url": "/videos/    .mp4",
    "fileName": "    .mp4"
  },
  {
    "id": "local-2",
    "title": "  ",
    "url": "/videos/  .mp4",
    "fileName": "  .mp4"
  },
  {
    "id": "local-3",
    "title": " ",
    "url": "/videos/ .mp4",
    "fileName": " .mp4"
  },
  {
    "id": "local-4",
    "title": "3D Shapes",
    "url": "/videos/3D shapes.mp4",
    "fileName": "3D shapes.mp4"
  },
  {
    "id": "local-5",
    "title": "Abstract",
    "url": "/videos/Abstract.mp4",
    "fileName": "Abstract.mp4"
  },
  {
    "id": "local-6",
    "title": "Advanced 3D",
    "url": "/videos/Advanced 3D.mp4",
    "fileName": "Advanced 3D.mp4"
  },
  {
    "id": "local-7",
    "title": "Aki   Juice WRLD   Cigarettes 4K #scm #amv #edit",
    "url": "/videos/Aki - Juice WRLD - Cigarettes 4K #scm #amv #edit.mp4",
    "fileName": "Aki - Juice WRLD - Cigarettes 4K #scm #amv #edit.mp4"
  },
  {
    "id": "local-8",
    "title": "Full Screen Vr.",
    "url": "/videos/Full screen vr..mp4",
    "fileName": "Full screen vr..mp4"
  },
  {
    "id": "local-9",
    "title": "Just For Fun ",
    "url": "/videos/Just for Fun .mp4",
    "fileName": "Just for Fun .mp4"
  },
  {
    "id": "local-10",
    "title": "Recent Frames Cool Banne Ke Liye Ye Sab Caption Likhna Padta HIB RM  @aiasvein",
    "url": "/videos/Recent Frames Cool banne ke liye ye sab caption likhna padta hIB-RM- @aiasvein.mp4",
    "fileName": "Recent Frames Cool banne ke liye ye sab caption likhna padta hIB-RM- @aiasvein.mp4"
  },
  {
    "id": "local-11",
    "title": "Saare Cheezon Ko Beech Me Chhor Dene Ki Adat Ho Gai Hrm Ib @infinityy Amv",
    "url": "/videos/Saare cheezon ko beech me chhor dene ki adat ho gai hrm-ib-@infinityy_amv.mp4",
    "fileName": "Saare cheezon ko beech me chhor dene ki adat ho gai hrm-ib-@infinityy_amv.mp4"
  },
  {
    "id": "local-12",
    "title": "Tek It Typography Edit #4k #3d",
    "url": "/videos/Tek It Typography edit #4k #3d.mp4",
    "fileName": "Tek It Typography edit #4k #3d.mp4"
  },
  {
    "id": "local-13",
    "title": "Tried Something New",
    "url": "/videos/Tried something new.mp4",
    "fileName": "Tried something new.mp4"
  },
  {
    "id": "local-14",
    "title": "UI Animation",
    "url": "/videos/UI animation.mp4",
    "fileName": "UI animation.mp4"
  },
  {
    "id": "local-15",
    "title": "P",
    "url": "/videos/p.mp4",
    "fileName": "p.mp4"
  }
]